django_collect_offline_files/__init__.py
django_collect_offline_files/action_handler.py
django_collect_offline_files/admin_site.py
django_collect_offline_files/apps.py
django_collect_offline_files/confirmation.py
django_collect_offline_files/constants.py
django_collect_offline_files/loggers.py
django_collect_offline_files/patterns.py
django_collect_offline_files/sftp_client.py
django_collect_offline_files/ssh_client.py
django_collect_offline_files/urls.py
django_collect_offline_files/admin/__init__.py
django_collect_offline_files/admin/exported_transaction_file_history_admin.py
django_collect_offline_files/admin/imported_transaction_file_history_admin.py
django_collect_offline_files/file_queues/__init__.py
django_collect_offline_files/file_queues/base_file_queue.py
django_collect_offline_files/file_queues/deserialize_transactions_file_queue.py
django_collect_offline_files/file_queues/exceptions.py
django_collect_offline_files/file_queues/file_queue_handlers.py
django_collect_offline_files/file_queues/incoming_transactions_file_queue.py
django_collect_offline_files/file_queues/process_queue.py
django_collect_offline_files/management/__init__.py
django_collect_offline_files/management/commands/__init__.py
django_collect_offline_files/management/commands/check_pending_files.py
django_collect_offline_files/management/commands/deserialize_observer.py
django_collect_offline_files/management/commands/export_transactions.py
django_collect_offline_files/management/commands/incoming_observer.py
django_collect_offline_files/migrations/0001_initial.py
django_collect_offline_files/migrations/0002_auto_20180731_2241.py
django_collect_offline_files/migrations/0003_auto_20180802_0224.py
django_collect_offline_files/migrations/0004_auto_20190305_0123.py
django_collect_offline_files/migrations/__init__.py
django_collect_offline_files/models/__init__.py
django_collect_offline_files/models/exported_transaction_file_history.py
django_collect_offline_files-0.1.27.dist-info/AUTHORS
django_collect_offline_files-0.1.27.dist-info/LICENSE
django_collect_offline_files-0.1.27.dist-info/METADATA
django_collect_offline_files-0.1.27.dist-info/WHEEL
django_collect_offline_files-0.1.27.dist-info/top_level.txt
django_collect_offline_files-0.1.27.dist-info/RECORD
