Metadata-Version: 2.1
Name: django-collect-offline-files
Version: 0.1.27
Summary: Add file-based data transfer to server for offline-use
Home-page: https://github.com/erikvw/django-collect-offline-files
Author: Erik van Widenfelt
Author-email: ew2789@gmail.com
License: GPL license, see LICENSE
Keywords: django data offline-use
Platform: UNKNOWN
Classifier: Environment :: Web Environment
Classifier: Framework :: Django
Classifier: Intended Audience :: Developers
Classifier: Intended Audience :: Science/Research
Classifier: License :: OSI Approved :: GNU General Public License v3 (GPLv3)
Classifier: Operating System :: OS Independent
Classifier: Programming Language :: Python :: 3.6
Classifier: Programming Language :: Python :: 3.7
Classifier: Topic :: Internet :: WWW/HTTP
Classifier: Topic :: Internet :: WWW/HTTP :: Dynamic Content
Requires-Dist: djangorestframework
Requires-Dist: django-cors-headers
Requires-Dist: requests
Requires-Dist: paramiko
Requires-Dist: hurry.filesize
Requires-Dist: watchdog
Requires-Dist: django-collect-offline
Requires-Dist: edc-device
Requires-Dist: edc-identifier
